[
    {"_id":{"$oid":"665ee3a9e983f4be83636ce8"},"title":"poco m3","brand":"xiaomi","price":"13000","description":"Hp Elitebook 840 G5 Laptop 8th Gen Core i5 Processor  (4 CPU @2.7ghz) 256gb SSD 500gb HDD. 8gb RAM  Keyboard Light 14” FHD Screen Fingerprint  HDMI SIM card slot Type C Port Very clean  4 hours battery life. Full box available.  Very urgent money need. 🥺","image_url":"https://scontent.fdac178-1.fna.fbcdn.net/v/t45.5328-4/445867181_1217840806247823_6611710320640704696_n.jpg?stp=dst-jpg_p720x720&_nc_cat=103&ccb=1-7&_nc_sid=247b10&_nc_eui2=AeFFTTsr2QZT30kbwBue4pMYp-k9-R2bxtKn6T35HZvG0lWoHvHoPoGbcQiEADcuBTVqKVRTdpyjwtt-NOUbvoBu&_nc_ohc=Ii-i5GbVTAIQ7kNvgGbWbLS&_nc_ht=scontent.fdac178-1.fna&oh=00_AYCP02_0KEhyswMeZIEFNWtZMyxFHs_dTkbKp1B4XgHREw&oe=6664A498","email":"abc@gmail.com"},
    {"_id":{"$oid":"665ee3a9e983f4be83636ce8"},"title":"poco m3","brand":"xiaomi","price":"13000","description":"Hp Elitebook 840 G5 Laptop 8th Gen Core i5 Processor  (4 CPU @2.7ghz) 256gb SSD 500gb HDD. 8gb RAM  Keyboard Light 14” FHD Screen Fingerprint  HDMI SIM card slot Type C Port Very clean  4 hours battery life. Full box available.  Very urgent money need. 🥺","image_url":"https://scontent.fdac178-1.fna.fbcdn.net/v/t45.5328-4/445867181_1217840806247823_6611710320640704696_n.jpg?stp=dst-jpg_p720x720&_nc_cat=103&ccb=1-7&_nc_sid=247b10&_nc_eui2=AeFFTTsr2QZT30kbwBue4pMYp-k9-R2bxtKn6T35HZvG0lWoHvHoPoGbcQiEADcuBTVqKVRTdpyjwtt-NOUbvoBu&_nc_ohc=Ii-i5GbVTAIQ7kNvgGbWbLS&_nc_ht=scontent.fdac178-1.fna&oh=00_AYCP02_0KEhyswMeZIEFNWtZMyxFHs_dTkbKp1B4XgHREw&oe=6664A498","email":"abc@gmail.com"}
]